{"stats":{"minecraft:used":{"minecraft:oak_log":4,"minecraft:netherite_shovel":2210,"minecraft:oak_planks":3,"minecraft:netherite_axe":134,"minecraft:spruce_planks":2,"minecraft:spruce_sapling":47,"minecraft:torch":3,"minecraft:sand":1,"minecraft:dirt":4,"minecraft:crafting_table":1,"minecraft:oak_sapling":6,"minecraft:egg":2,"minecraft:cooked_beef":18,"minecraft:spruce_log":1},"minecraft:custom":{"minecraft:time_since_rest":42382,"minecraft:interact_with_smithing_table":1,"minecraft:damage_taken":2089,"minecraft:interact_with_furnace":14,"minecraft:sprint_one_cm":331933,"minecraft:walk_one_cm":702362,"minecraft:mob_kills":1,"minecraft:drop":458,"minecraft:damage_dealt":216,"minecraft:swim_one_cm":94746,"minecraft:talked_to_villager":1,"minecraft:fly_one_cm":237429,"minecraft:open_chest":25,"minecraft:play_one_minute":149966,"minecraft:crouch_one_cm":5906,"minecraft:sneak_time":2756,"minecraft:deaths":3,"minecraft:walk_under_water_one_cm":27977,"minecraft:jump":2068,"minecraft:leave_game":4,"minecraft:time_since_death":73998,"minecraft:walk_on_water_one_cm":28884,"minecraft:sleep_in_bed":6,"minecraft:climb_one_cm":550,"minecraft:fall_one_cm":64259},"minecraft:picked_up":{"minecraft:birch_log":10,"minecraft:stick":32,"minecraft:crafting_table":1,"minecraft:cooked_beef":65,"minecraft:chainmail_boots":1,"minecraft:stone_brick_slab":20,"minecraft:torch":3,"minecraft:spruce_stairs":2,"minecraft:netherite_shovel":2,"minecraft:sand":2182,"minecraft:stone_brick_stairs":18,"minecraft:oak_log":54,"minecraft:spruce_sapling":40,"minecraft:spruce_log":132,"minecraft:dirt":485,"minecraft:quartz_slab":2,"minecraft:cactus":2,"minecraft:rotten_flesh":11,"minecraft:spruce_planks":17,"minecraft:netherite_axe":1,"minecraft:oak_sapling":32,"minecraft:birch_sapling":4,"minecraft:oak_planks":10,"minecraft:egg":2},"minecraft:dropped":{"minecraft:dirt":413,"minecraft:cooked_beef":25,"minecraft:oak_log":5,"minecraft:spruce_planks":8,"minecraft:oak_sapling":5,"minecraft:rotten_flesh":10,"minecraft:oak_planks":7,"minecraft:netherite_shovel":1,"minecraft:spruce_log":130,"minecraft:sand":2,"minecraft:cactus":2,"minecraft:stone_brick_stairs":14,"minecraft:quartz_slab":2,"minecraft:spruce_sapling":3,"minecraft:stone_brick_slab":16,"minecraft:stick":21},"minecraft:killed":{"minecraft:zombie":1},"minecraft:broken":{"minecraft:chainmail_boots":1},"minecraft:killed_by":{"minecraft:player":1,"minecraft:pillager":1,"minecraft:enderman":1},"minecraft:mined":{"minecraft:oak_sapling":4,"minecraft:spruce_sapling":11,"minecraft:birch_log":10,"minecraft:spruce_log":81,"minecraft:birch_leaves":5,"minecraft:grass":3,"minecraft:grass_block":2,"minecraft:oak_log":49,"minecraft:dead_bush":3,"minecraft:sand":2208,"minecraft:oak_leaves":8}},"DataVersion":2580}